gnetcli_adapter/__init__.py
gnetcli_adapter/gnetcli_adapter.py
gnetcli_adapter/progress_tracker.py
gnetcli_adapter-2.6.0.dist-info/entry_points.txt
gnetcli_adapter-2.6.0.dist-info/licenses/LICENSE
gnetcli_adapter-2.6.0.dist-info/WHEEL
gnetcli_adapter-2.6.0.dist-info/METADATA
gnetcli_adapter-2.6.0.dist-info/RECORD
